[{"id":1,"filename":"1.1.1","english":"_am a girl.","correct":"I","wrong":"my","vietnamese":"Tôi là một cô gái."},
{"id":1,"filename":"1.1.2","english":"_is a husband.","correct":"he","wrong":"his","vietnamese":"Anh ấy là một người chồng."},
{"id":1,"filename":"1.1.3","english":"This man is_brother.","correct":"their","wrong":"they","vietnamese":"Người đàn ông này là anh trai của họ."},
{"id":1,"filename":"1.1.4","english":"My brother and sister_young.","correct":"are","wrong":"is  ","vietnamese":"Anh trai và chị gái của tôi trẻ."},
{"id":1,"filename":"1.1.5","english":"_husband is a man.","correct":"my","wrong":"I ","vietnamese":"Chồng của tôi là một người đàn ông."},
{"id":2,"filename":"2.1.1","english":"He is_dentist.","correct":"a  ","wrong":"an","vietnamese":"Anh ấy là một nha sỹ."},
{"id":2,"filename":"2.1.2","english":"Her husband is a_.","correct":"manager","wrong":"managers.","vietnamese":"Chồng của cô ấy là một nhà quản lý."},
{"id":2,"filename":"2.1.3","english":"His wife is_actress.","correct":"an","wrong":"a  ","vietnamese":"Vợ của anh ấy là một diễn viên nữ."},
{"id":2,"filename":"2.1.4","english":"Her_are musicians.","correct":"friends","wrong":"friend","vietnamese":"Các bạn của cô ấy là những nhạc sỹ."},
{"id":2,"filename":"2.1.5","english":"The dancers_my aunt.","correct":"are","wrong":"is  ","vietnamese":"Những vũ công là dì của tôi."},
{"id":3,"filename":"3.1.1","english":"I_your father.","correct":"am not","wrong":"is not","vietnamese":"Tôi không phải là bố của bạn."},
{"id":3,"filename":"3.1.2","english":"I_young.","correct":"am ","wrong":"is","vietnamese":"Tôi trẻ."},
{"id":3,"filename":"3.1.3","english":"He is_.","correct":"a boy","wrong":"a boys","vietnamese":"Anh ấy là một cậu bé."},
{"id":3,"filename":"3.1.4","english":"They are not_.","correct":"doctors","wrong":"doctor","vietnamese":"Họ không phải là những bác sỹ."},
{"id":3,"filename":"3.1.5","english":"_are at school.","correct":"his sisters","wrong":"his sister","vietnamese":"Những chị gái của anh ấy ở trường."},
{"id":4,"filename":"4.1.1","english":"I often_TV.","correct":"watch","wrong":"watchs","vietnamese":"Tôi thường xem tivi."},
{"id":4,"filename":"4.1.2","english":"You_water.","correct":"drink","wrong":"drinks","vietnamese":"Bạn uống nước."},
{"id":4,"filename":"4.1.3","english":"We_hate carefless girls.","correct":"do not","wrong":"does not","vietnamese":"Chúng tôi không ghét những cô gái cẩu thả."},
{"id":4,"filename":"4.1.4","english":"We_a big cake.","correct":"buy","wrong":"buys","vietnamese":"Chúng tôi mua một chiếc bánh lớn."},
{"id":4,"filename":"4.1.5","english":"The actor and actress_movies.","correct":"like","wrong":"likes","vietnamese":"Diễn viên nam và diễn viên nữa thích những bộ phim."},
{"id":5,"filename":"5.1.1","english":"She_English.","correct":"speaks","wrong":"speak","vietnamese":"Cô ấy nói tiếng Anh."},
{"id":5,"filename":"5.1.2","english":"He_his hometown weekly.","correct":"visits","wrong":"visit","vietnamese":"Anh ấy thăm quê hương của anh ấy hàng tuần."},
{"id":5,"filename":"5.1.3","english":"Their father_watch movies in the evening.","correct":"does not","wrong":"do not","vietnamese":"Bố của họ không xem phim vào buổi tối."},
{"id":5,"filename":"5.1.4","english":"Her brother_home early.","correct":"goes","wrong":"go","vietnamese":"Anh trai của cô ấy đi về nhà sớm."},
{"id":5,"filename":"5.1.5","english":"A friendly farmer_newspaper.","correct":"has a","wrong":"have a","vietnamese":"Một người nông dân thân thiện có một tờ báo."},
{"id":6,"filename":"6.1.1","english":"You can_slowly.","correct":"swim","wrong":"swims","vietnamese":"Bạn có thể bơi chậm."},
{"id":6,"filename":"6.1.2","english":"We should_English.","correct":"speak ","wrong":"speaks","vietnamese":"Chúng ta nên nói tiếng Anh."},
{"id":6,"filename":"6.1.3","english":"She can_.","correct":"dance","wrong":"dances","vietnamese":"Cô ấy có thể múa."},
{"id":6,"filename":"6.1.4","english":"A manager should_fast.","correct":"not speak","wrong":"not speaks","vietnamese":"Một nhà quản lý không nên nói nhanh."},
{"id":6,"filename":"6.1.5","english":"My brother can eat juice and vegetables_.","correct":"well","wrong":"good","vietnamese":"Anh trai của tôi có thể ăn hoa quả và rau tốt."},
{"id":7,"filename":"7.1.1","english":"This_my pen.","correct":"is","wrong":"are","vietnamese":"Đây là cái bút của tôi"},
{"id":7,"filename":"7.1.2","english":"That is not_, that is a window.","correct":"a door","wrong":"an door","vietnamese":"Kia không phải là một cái cửa chính, kia là một cái cửa sổ."},
{"id":7,"filename":"7.1.3","english":"These are not black_.","correct":"tables","wrong":"table","vietnamese":"Đây không phải những cái bàn màu đen."},
{"id":7,"filename":"7.1.4","english":"Those_not green doors.","correct":"are","wrong":"is","vietnamese":"Kia không phải là những cái cửa màu xanh."},
{"id":7,"filename":"7.1.5","english":"_are his oranges.","correct":"those","wrong":"that","vietnamese":"Kia là những quả cam của anh ấy."},
{"id":8,"filename":"8.1.1","english":"There_not an apple, there is an orange.","correct":"is","wrong":"are","vietnamese":"Không có một quả táo, có một quả cam."},
{"id":8,"filename":"8.1.2","english":"There are_.","correct":"cars","wrong":"car","vietnamese":"Có những chiếc xe ô tô."},
{"id":8,"filename":"8.1.3","english":"There is a manager_the company.","correct":"in","wrong":"on","vietnamese":"Có một nhà quản lý trong công ty."},
{"id":8,"filename":"8.1.4","english":"There are_and nurses in the hospital.","correct":"doctors","wrong":"doctor","vietnamese":"Có những bác sỹ và những y tá trong bệnh viện."},
{"id":8,"filename":"8.1.5","english":"There_lions.","correct":"are not","wrong":"is not","vietnamese":"Không có những con sư tử."}]